duvet/__init__.py
lightpick-0.0.1b0.dist-info/METADATA
lightpick-0.0.1b0.dist-info/WHEEL
lightpick-0.0.1b0.dist-info/RECORD
